noder/_version.pyi
noder/core.cpython-313-darwin.so
noder/LICENSE
noder/_core.pyi
noder/_version.py
noder/tests.cpython-313-darwin.so
noder/__init__.py
noder/README.md
noder/libcore_shared.dylib
noder/array/__init__.py
noder/array/data_types.py
noder/array/array.py
noder/include/array/array.hpp
noder/include/array/assertions.hpp
noder/include/array/factory/c_to_py.hpp
noder/include/array/factory/matrices.hpp
noder/include/array/factory/strings.hpp
noder/include/array/factory/vectors.hpp
noder/include/io/io.hpp
noder/include/io/cgns/node_pycgns_converter_pybind.hpp
noder/include/io/cgns/node_pycgns_converter.hpp
noder/include/utils/data_types.hpp
noder/include/utils/template_binder.hpp
noder/include/utils/string.hpp
noder/include/utils/comparator.hpp
noder/include/utils/compat.hpp
noder/include/utils/template_instantiator.hpp
noder/include/node/node.hpp
noder/include/node/navigation.hpp
noder/include/data/data_factory.hpp
noder/include/data/data.hpp
noder/tests/c++/test_core_pybind.cpp
noder/tests/c++/array/test_array.cpp
noder/tests/c++/array/test_array_pybind.hpp
noder/tests/c++/array/test_assertions.cpp
noder/tests/c++/array/test_modifiers.hpp
noder/tests/c++/array/test_modifiers_pybind.hpp
noder/tests/c++/array/test_array_data_accessors.cpp
noder/tests/c++/array/test_printer_pybind.hpp
noder/tests/c++/array/test_comparisons_pybind.hpp
noder/tests/c++/array/test_comparisons.cpp
noder/tests/c++/array/test_printer.cpp
noder/tests/c++/array/test_assertions_pybind.hpp
noder/tests/c++/array/test_comparisons.hpp
noder/tests/c++/array/test_printer.hpp
noder/tests/c++/array/test_array_data_accessors_pybind.hpp
noder/tests/c++/array/test_array.hpp
noder/tests/c++/array/test_assertions.hpp
noder/tests/c++/array/test_modifiers.cpp
noder/tests/c++/array/test_array_data_accessors.hpp
noder/tests/c++/array/factory/test_strings.cpp
noder/tests/c++/array/factory/test_matrices.cpp
noder-1.0.1.dist-info/RECORD
noder-1.0.1.dist-info/WHEEL
noder-1.0.1.dist-info/METADATA
noder-1.0.1.dist-info/licenses/LICENSE
