Metadata-Version: 2.1
Name: noder
Version: 1.0.1
Summary: A library for efficient large data operations designed for handling arrays hierarchically using an object-oriented approach
Author-Email: Luis Bernardos <luisfco.bernardos@gmail.com>
License:                    GNU LESSER GENERAL PUBLIC LICENSE
Classifier: Development Status :: 1 - Planning
Classifier: Intended Audience :: Science/Research
Classifier: Intended Audience :: Developers
Classifier: Operating System :: OS Independent
Classifier: Programming Language :: Python :: 3 :: Only
Classifier: Programming Language :: Python :: 3.8
Classifier: Programming Language :: Python :: 3.9
Classifier: Programming Language :: Python :: 3.10
Classifier: Programming Language :: Python :: 3.11
Classifier: Programming Language :: Python :: 3.12
Classifier: Topic :: Scientific/Engineering
Classifier: Typing :: Typed
Project-URL: Homepage, https://github.com/onera/noder
Project-URL: Bug Tracker, https://github.com/onera/noder/issues
Project-URL: Discussions, https://github.com/onera/noder/discussions
Project-URL: Changelog, https://github.com/onera/noder/releases
Requires-Python: >=3.8
Requires-Dist: numpy
Provides-Extra: test
Requires-Dist: pytest>=6; extra == "test"
Requires-Dist: pytest-cov>=3; extra == "test"
Provides-Extra: dev
Requires-Dist: pytest>=6; extra == "dev"
Requires-Dist: pytest-cov>=3; extra == "dev"
Provides-Extra: docs
Requires-Dist: sphinx>=7.0; extra == "docs"
Requires-Dist: myst_parser>=0.13; extra == "docs"
Requires-Dist: sphinx_copybutton; extra == "docs"
Requires-Dist: sphinx_autodoc_typehints; extra == "docs"
Requires-Dist: furo>=2023.08.17; extra == "docs"
